setup.py
simplesqltool/SqlUtil.py
simplesqltool/__init__.py
simplesqltool.egg-info/PKG-INFO
simplesqltool.egg-info/SOURCES.txt
simplesqltool.egg-info/dependency_links.txt
simplesqltool.egg-info/top_level.txt