Metadata-Version: 1.0
Name: simplesqltool
Version: 1.3
Summary: simpleutil tools for sql
Home-page: UNKNOWN
Author: Yong Wang
Author-email: ever0702@gmail.com
License: UNKNOWN
Platform: UNKNOWN
